dynakit/FE.py
dynakit/__init__.py
dynakit/_nbdev.py
dynakit/test.py
dynakit-0.0.3.dist-info/LICENSE
dynakit-0.0.3.dist-info/METADATA
dynakit-0.0.3.dist-info/WHEEL
dynakit-0.0.3.dist-info/entry_points.txt
dynakit-0.0.3.dist-info/top_level.txt
dynakit-0.0.3.dist-info/RECORD
