Metadata-Version: 2.1
Name: dynakit
Version: 0.0.3
Summary: Machine Learning Toolkit for LS-Dyna Simulations
Home-page: https://github.com/dynapy/dynakit/tree/main/
Author: Jobin
Author-email: jobin.john@chalmers.se
License: Apache Software License 2.0
Keywords: LS-Dyna,ML,FE
Platform: UNKNOWN
Classifier: Development Status :: 2 - Pre-Alpha
Classifier: Intended Audience :: Developers
Classifier: Natural Language :: English
Classifier: Programming Language :: Python :: 3.6
Classifier: Programming Language :: Python :: 3.7
Classifier: Programming Language :: Python :: 3.8
Classifier: License :: OSI Approved :: Apache Software License
Requires-Python: >=3.6
Requires-Dist: lasso-python (>=1.5.0)
Requires-Dist: diversipy (==0.8)
Requires-Dist: numpy (==1.20.1)
Requires-Dist: pandas (==1.1.5)
Requires-Dist: pyDOE (==0.3.8)
Requires-Dist: PyYAML (==5.4.1)
Requires-Dist: qd (==0.8.9)
Requires-Dist: scipy (==1.6.0)
